bsmcmp/__init__.py
bsmcmp/__main__.py
bsmcmp/ascii.py
bsmcmp/base.py
bsmcmp/csv.py
bsmcmp/grib2.py
bsmcmp/h5.py
bsmcmp/mat.py
bsmcmp/netcdf.py
bsmcmp/utility.py
bsmcmp/version.py
bsmcmp-0.0.5.dist-info/licenses/LICENSE
bsmcmp-0.0.5.dist-info/METADATA
bsmcmp-0.0.5.dist-info/WHEEL
bsmcmp-0.0.5.dist-info/entry_points.txt
bsmcmp-0.0.5.dist-info/top_level.txt
bsmcmp-0.0.5.dist-info/RECORD
