Metadata-Version: 2.4
Name: bsmcmp
Version: 0.0.5
Summary: bsmcmp is a tool to compare files
Author-email: Tianzhu Qiao <tq@feiyilin.com>
License: MIT License
Project-URL: Homepage, https://github.com/tianzhuqiao/bsmcmp
Classifier: Operating System :: OS Independent
Requires-Python: >=3.0
License-File: LICENSE
Requires-Dist: numpy
Requires-Dist: scipy
Requires-Dist: click>=8.1
Requires-Dist: pandas
Requires-Dist: netCDF4
Requires-Dist: charset_normalizer
Requires-Dist: h5py
Requires-Dist: packaging
Requires-Dist: netCDF4
Requires-Dist: tqdm
Requires-Dist: pyyaml
Requires-Dist: xarray
Requires-Dist: cfgrib
Dynamic: license-file
